irisml/tasks/create_azure_computervision_caption_model.py
irisml/tasks/create_azure_computervision_classification_model.py
irisml/tasks/create_azure_computervision_custom_model.py
irisml/tasks/create_azure_computervision_ocr_model.py
irisml/tasks/create_azure_computervision_product_recognizer_model.py
irisml/tasks/create_azure_computervision_vectorization_model.py
irisml/tasks/create_azure_customvision_docker_model.py
irisml/tasks/create_azure_customvision_model.py
irisml/tasks/create_azure_customvision_project.py
irisml/tasks/create_azure_documentintelligence_read_model.py
irisml/tasks/delete_azure_computervision_custom_model.py
irisml/tasks/delete_azure_customvision_project.py
irisml/tasks/export_azure_customvision_model.py
irisml/tasks/train_azure_computervision_custom_model.py
irisml/tasks/train_azure_customvision_project.py
irisml_tasks_azure_aiservices-0.0.2.dist-info/LICENSE
irisml_tasks_azure_aiservices-0.0.2.dist-info/METADATA
irisml_tasks_azure_aiservices-0.0.2.dist-info/WHEEL
irisml_tasks_azure_aiservices-0.0.2.dist-info/top_level.txt
irisml_tasks_azure_aiservices-0.0.2.dist-info/RECORD
