Metadata-Version: 2.2
Name: irisml-tasks-azure-aiservices
Version: 0.0.2
Requires-Python: >=3.10
License-File: LICENSE
Requires-Dist: irisml
Requires-Dist: Pillow
Requires-Dist: requests
Requires-Dist: tenacity
Requires-Dist: torchvision
